LICENSE
README.md
setup.cfg
setup.py
laneatt/__init__.py
laneatt/laneatt.py
laneatt.egg-info/PKG-INFO
laneatt.egg-info/SOURCES.txt
laneatt.egg-info/dependency_links.txt
laneatt.egg-info/requires.txt
laneatt.egg-info/top_level.txt
laneatt/config/backbones.yaml
laneatt/utils/__init__.py
laneatt/utils/anchors.py
laneatt/utils/dataset.py
laneatt/utils/focal_loss.py
laneatt/utils/logger.py
laneatt/utils/model_state.py