Metadata-Version: 2.1
Name: laneatt
Version: 1.3.1
Summary: A package to detect lane lines in images and videos
Home-page: https://github.com/PaoloReyes/RealTime-LaneATT
Download-URL: https://github.com/PaoloReyes/RealTime-LaneATT/archive/refs/tags/LaneATT-v1.2.tar.gz
Author: Paolo Reyes
Author-email: paolo.alfonso.reyes@gmail.com
License: MIT
Keywords: lanes,AI,greenhouse,detection,machine,learning,laneatt,lane,lines,line
Classifier: Development Status :: 5 - Production/Stable
Classifier: Intended Audience :: Developers
Classifier: Topic :: Software Development :: Build Tools
Classifier: License :: OSI Approved :: MIT License
Classifier: Programming Language :: Python :: 3
Classifier: Programming Language :: Python :: 3.12
License-File: LICENSE
Requires-Dist: filelock
Requires-Dist: fsspec
Requires-Dist: Jinja2
Requires-Dist: joblib
Requires-Dist: MarkupSafe
Requires-Dist: mpmath
Requires-Dist: networkx
Requires-Dist: numpy
Requires-Dist: nvidia-cublas-cu12
Requires-Dist: nvidia-cuda-cupti-cu12
Requires-Dist: nvidia-cuda-nvrtc-cu12
Requires-Dist: nvidia-cuda-runtime-cu12
Requires-Dist: nvidia-cudnn-cu12
Requires-Dist: nvidia-cufft-cu12
Requires-Dist: nvidia-curand-cu12
Requires-Dist: nvidia-cusolver-cu12
Requires-Dist: nvidia-cusparse-cu12
Requires-Dist: nvidia-nccl-cu12
Requires-Dist: nvidia-nvjitlink-cu12
Requires-Dist: nvidia-nvtx-cu12
Requires-Dist: opencv-python
Requires-Dist: pillow
Requires-Dist: PyYAML
Requires-Dist: scikit-learn
Requires-Dist: scipy
Requires-Dist: setuptools
Requires-Dist: sympy
Requires-Dist: threadpoolctl
Requires-Dist: torch
Requires-Dist: torchaudio
Requires-Dist: torchvision
Requires-Dist: tqdm
Requires-Dist: triton
Requires-Dist: typing_extensions
Requires-Dist: wheel
